MANIFEST.in
setup.py
systray_file_watcher.egg-info/PKG-INFO
systray_file_watcher.egg-info/SOURCES.txt
systray_file_watcher.egg-info/dependency_links.txt
systray_file_watcher.egg-info/entry_points.txt
systray_file_watcher.egg-info/top_level.txt
systray_file_watcher_app/__init__.py
systray_file_watcher_app/application.py
systray_file_watcher_app/icons/expiring_soon.png
systray_file_watcher_app/icons/idle.png
systray_file_watcher_app/icons/updating.png