Metadata-Version: 1.1
Name: systray-file-watcher
Version: 0.4.0
Summary: File modification notifier in your system tray
Home-page: http://bitbucket.org/latestrevision/systray-file-watcher/
Author: Adam Coddington
Author-email: me@adamcoddington.net
License: UNKNOWN
Platform: UNKNOWN
Classifier: License :: OSI Approved :: MIT License
Classifier: Operating System :: OS Independent
Classifier: Programming Language :: Python
Classifier: Topic :: Utilities
